chatclicks/__init__.py
chatclicks-0.4.6.dist-info/METADATA
chatclicks-0.4.6.dist-info/WHEEL
chatclicks-0.4.6.dist-info/top_level.txt
chatclicks-0.4.6.dist-info/RECORD
