Metadata-Version: 2.1
Name: chatclicks
Version: 0.4.6
Summary: A client for the Twitch Extension named Chat Clicks
Home-page: https://github.com/WillPiledriver/chatclicks
Author: WillPiledriver
Author-email: willpiledriver <smifthsmurfth@gmail.com>
License: MIT
Project-URL: Homepage, https://github.com/WillPiledriver/chatclicks
Keywords: twitch,extension,client,chat
Classifier: Programming Language :: Python :: 3
Classifier: License :: OSI Approved :: MIT License
Classifier: Operating System :: OS Independent
Requires-Python: >=3.5
Requires-Dist: python-socketio
Requires-Dist: scikit-learn
Requires-Dist: numpy
Requires-Dist: aiohttp
Requires-Dist: asyncio
Requires-Dist: screeninfo
